<?xml version="1.0" encoding="utf-8"?>
<spacedivisionmap width="16000" height="16000">
	<sdqnode id="0" parentid="0" recttop="16000" rectleft="0" rectbottom="0" rectright="16000">
		<sdqnode id="1" parentid="0" recttop="16000" rectleft="0" rectbottom="8000" rectright="8000"/>
		<sdqnode id="2" parentid="0" recttop="16000" rectleft="8000" rectbottom="8000" rectright="16000"/>
		<sdqnode id="3" parentid="0" recttop="8000" rectleft="8000" rectbottom="0" rectright="16000"/>
		<sdqnode id="4" parentid="0" recttop="8000" rectleft="0" rectbottom="0" rectright="8000">
			<sdqnode id="41" parentid="4" recttop="8000" rectleft="0" rectbottom="4000" rectright="4000"/>
			<sdqnode id="42" parentid="4" recttop="8000" rectleft="4000" rectbottom="4000" rectright="8000"/>
			<sdqnode id="43" parentid="4" recttop="4000" rectleft="4000" rectbottom="0" rectright="8000"/>
			<sdqnode id="44" parentid="4" recttop="4000" rectleft="0" rectbottom="0" rectright="4000">
				<sdqnode id="441" parentid="44" recttop="4000" rectleft="0" rectbottom="2000" rectright="2000"/>
				<sdqnode id="442" parentid="44" recttop="4000" rectleft="2000" rectbottom="2000" rectright="4000"/>
				<sdqnode id="443" parentid="44" recttop="2000" rectleft="2000" rectbottom="0" rectright="4000">
					<sdqnode id="4431" parentid="443" recttop="2000" rectleft="2000" rectbottom="1000" rectright="3000"/>
					<sdqnode id="4432" parentid="443" recttop="2000" rectleft="3000" rectbottom="1000" rectright="4000"/>
					<sdqnode id="4433" parentid="443" recttop="1000" rectleft="3000" rectbottom="0" rectright="4000"/>
					<sdqnode id="4434" parentid="443" recttop="1000" rectleft="2000" rectbottom="0" rectright="3000">
						<sdqnode id="44341" parentid="4434" recttop="1000" rectleft="2000" rectbottom="500" rectright="2500"/>
						<sdqnode id="44342" parentid="4434" recttop="1000" rectleft="2500" rectbottom="500" rectright="3000"/>
						<sdqnode id="44343" parentid="4434" recttop="500" rectleft="2500" rectbottom="0" rectright="3000">
							<sdqnode id="443431" parentid="44343" recttop="500" rectleft="2500" rectbottom="250" rectright="2750" bodyid="45" tileid="78" tileid="79" tileid="80" tileid="81" tileid="148" tileid="149" tileid="150" tileid="151" tileid="174" tileid="175" tileid="176" tileid="177" tileid="196" tileid="197" tileid="198" tileid="199" tileid="222" tileid="223" tileid="224" tileid="225" tileid="250" tileid="251" tileid="277" tileid="278" tileid="304" tileid="305"/>
							<sdqnode id="443432" parentid="44343" recttop="500" rectleft="2750" rectbottom="250" rectright="3000"/>
							<sdqnode id="443433" parentid="44343" recttop="250" rectleft="2750" rectbottom="0" rectright="3000"/>
							<sdqnode id="443434" parentid="44343" recttop="250" rectleft="2500" rectbottom="0" rectright="2750" bodyid="27" bodyid="44" tileid="304" tileid="305" tileid="335" tileid="336" tileid="337" tileid="338" tileid="339" tileid="340" tileid="371" tileid="372" tileid="373" tileid="374" tileid="375" tileid="376" tileid="398" tileid="399" tileid="400" tileid="401" tileid="402" tileid="403" tileid="427" tileid="428" tileid="429" tileid="430" tileid="431" tileid="432" tileid="461" tileid="462" tileid="463" tileid="464" tileid="543" tileid="544" tileid="545" tileid="546" tileid="625" tileid="626" tileid="627" tileid="628"/>
						</sdqnode>
						<sdqnode id="44344" parentid="4434" recttop="500" rectleft="2000" rectbottom="0" rectright="2500">
							<sdqnode id="443441" parentid="44344" recttop="500" rectleft="2000" rectbottom="250" rectright="2250" bodyid="47" tileid="62" tileid="63" tileid="64" tileid="65" tileid="66" tileid="67" tileid="68" tileid="69" tileid="70" tileid="134" tileid="135" tileid="136" tileid="137" tileid="138" tileid="139" tileid="140" tileid="173"/>
							<sdqnode id="443442" parentid="44344" recttop="500" rectleft="2250" rectbottom="250" rectright="2500" bodyid="45" bodyid="47" tileid="70" tileid="71" tileid="72" tileid="73" tileid="74" tileid="75" tileid="76" tileid="77" tileid="78" tileid="140" tileid="141" tileid="142" tileid="143" tileid="144" tileid="145" tileid="146" tileid="147" tileid="148" tileid="174" tileid="196" tileid="222"/>
							<sdqnode id="443443" parentid="44344" recttop="250" rectleft="2250" rectbottom="0" rectright="2500" bodyid="27" bodyid="43" bodyid="44" tileid="331" tileid="332" tileid="333" tileid="334" tileid="335" tileid="371" tileid="398" tileid="427" tileid="461" tileid="535" tileid="536" tileid="537" tileid="538" tileid="539" tileid="540" tileid="541" tileid="542" tileid="543" tileid="617" tileid="618" tileid="619" tileid="620" tileid="621" tileid="622" tileid="623" tileid="624" tileid="625"/>
							<sdqnode id="443444" parentid="44344" recttop="250" rectleft="2000" rectbottom="0" rectright="2250" bodyid="27" tileid="527" tileid="528" tileid="529" tileid="530" tileid="531" tileid="532" tileid="533" tileid="534" tileid="535" tileid="609" tileid="610" tileid="611" tileid="612" tileid="613" tileid="614" tileid="615" tileid="616" tileid="617"/>
						</sdqnode>
					</sdqnode>
				</sdqnode>
				<sdqnode id="444" parentid="44" recttop="2000" rectleft="0" rectbottom="0" rectright="2000">
					<sdqnode id="4441" parentid="444" recttop="2000" rectleft="0" rectbottom="1000" rectright="1000"/>
					<sdqnode id="4442" parentid="444" recttop="2000" rectleft="1000" rectbottom="1000" rectright="2000"/>
					<sdqnode id="4443" parentid="444" recttop="1000" rectleft="1000" rectbottom="0" rectright="2000">
						<sdqnode id="44431" parentid="4443" recttop="1000" rectleft="1000" rectbottom="500" rectright="1500"/>
						<sdqnode id="44432" parentid="4443" recttop="1000" rectleft="1500" rectbottom="500" rectright="2000"/>
						<sdqnode id="44433" parentid="4443" recttop="500" rectleft="1500" rectbottom="0" rectright="2000">
							<sdqnode id="444331" parentid="44433" recttop="500" rectleft="1500" rectbottom="250" rectright="1750" tileid="46" tileid="47" tileid="48" tileid="49" tileid="50" tileid="51" tileid="52" tileid="53" tileid="54" tileid="122" tileid="123" tileid="124" tileid="125" tileid="126" tileid="127" tileid="128" tileid="171"/>
							<sdqnode id="444332" parentid="44433" recttop="500" rectleft="1750" rectbottom="250" rectright="2000" tileid="54" tileid="55" tileid="56" tileid="57" tileid="58" tileid="59" tileid="60" tileid="61" tileid="62" tileid="128" tileid="129" tileid="130" tileid="131" tileid="132" tileid="133" tileid="134" tileid="172"/>
							<sdqnode id="444333" parentid="44433" recttop="250" rectleft="1750" rectbottom="0" rectright="2000" bodyid="27" tileid="519" tileid="520" tileid="521" tileid="522" tileid="523" tileid="524" tileid="525" tileid="526" tileid="527" tileid="601" tileid="602" tileid="603" tileid="604" tileid="605" tileid="606" tileid="607" tileid="608" tileid="609"/>
							<sdqnode id="444334" parentid="44433" recttop="250" rectleft="1500" rectbottom="0" rectright="1750" bodyid="27" bodyid="70" tileid="366" tileid="367" tileid="368" tileid="369" tileid="370" tileid="511" tileid="512" tileid="513" tileid="514" tileid="515" tileid="516" tileid="517" tileid="518" tileid="519" tileid="593" tileid="594" tileid="595" tileid="596" tileid="597" tileid="598" tileid="599" tileid="600" tileid="601"/>
						</sdqnode>
						<sdqnode id="44434" parentid="4443" recttop="500" rectleft="1000" rectbottom="0" rectright="1500">
							<sdqnode id="444341" parentid="44434" recttop="500" rectleft="1000" rectbottom="250" rectright="1250" bodyid="37" bodyid="39" bodyid="41" bodyid="42" tileid="31" tileid="32" tileid="33" tileid="34" tileid="35" tileid="36" tileid="37" tileid="38" tileid="39" tileid="111" tileid="112" tileid="113" tileid="114" tileid="115" tileid="116" tileid="117" tileid="169" tileid="194" tileid="220" tileid="246" tileid="247" tileid="273" tileid="274" tileid="300" tileid="301"/>
							<sdqnode id="444342" parentid="44434" recttop="500" rectleft="1250" rectbottom="250" rectright="1500" bodyid="38" bodyid="40" tileid="39" tileid="40" tileid="41" tileid="42" tileid="43" tileid="44" tileid="45" tileid="46" tileid="117" tileid="118" tileid="119" tileid="120" tileid="121" tileid="122" tileid="170" tileid="195" tileid="221" tileid="248" tileid="249" tileid="275" tileid="276" tileid="302" tileid="303"/>
							<sdqnode id="444343" parentid="44434" recttop="250" rectleft="1250" rectbottom="0" rectright="1500" bodyid="27" bodyid="36" bodyid="38" tileid="302" tileid="303" tileid="329" tileid="330" tileid="364" tileid="365" tileid="456" tileid="457" tileid="458" tileid="459" tileid="460" tileid="504" tileid="505" tileid="506" tileid="507" tileid="508" tileid="509" tileid="510" tileid="511" tileid="586" tileid="587" tileid="588" tileid="589" tileid="590" tileid="591" tileid="592" tileid="593"/>
							<sdqnode id="444344" parentid="44434" recttop="250" rectleft="1000" rectbottom="0" rectright="1250" bodyid="27" bodyid="35" bodyid="36" bodyid="37" tileid="300" tileid="301" tileid="326" tileid="327" tileid="328" tileid="361" tileid="362" tileid="363" tileid="397" tileid="426" tileid="454" tileid="455" tileid="456" tileid="496" tileid="497" tileid="498" tileid="499" tileid="500" tileid="501" tileid="502" tileid="503" tileid="504" tileid="578" tileid="579" tileid="580" tileid="581" tileid="582" tileid="583" tileid="584" tileid="585" tileid="586"/>
						</sdqnode>
					</sdqnode>
					<sdqnode id="4444" parentid="444" recttop="1000" rectleft="0" rectbottom="0" rectright="1000">
						<sdqnode id="44441" parentid="4444" recttop="1000" rectleft="0" rectbottom="500" rectright="500"/>
						<sdqnode id="44442" parentid="4444" recttop="1000" rectleft="500" rectbottom="500" rectright="1000"/>
						<sdqnode id="44443" parentid="4444" recttop="500" rectleft="500" rectbottom="0" rectright="1000">
							<sdqnode id="444431" parentid="44443" recttop="500" rectleft="500" rectbottom="250" rectright="750" bodyid="26" bodyid="41" tileid="15" tileid="16" tileid="17" tileid="18" tileid="19" tileid="20" tileid="21" tileid="22" tileid="23" tileid="97" tileid="98" tileid="99" tileid="100" tileid="101" tileid="102" tileid="103" tileid="167" tileid="168" tileid="193" tileid="215" tileid="241" tileid="267" tileid="294"/>
							<sdqnode id="444432" parentid="44443" recttop="500" rectleft="750" rectbottom="250" rectright="1000" bodyid="33" bodyid="34" bodyid="41" tileid="23" tileid="24" tileid="25" tileid="26" tileid="27" tileid="28" tileid="29" tileid="30" tileid="31" tileid="103" tileid="104" tileid="105" tileid="106" tileid="107" tileid="108" tileid="109" tileid="110" tileid="111" tileid="216" tileid="217" tileid="218" tileid="219" tileid="242" tileid="243" tileid="244" tileid="245" tileid="268" tileid="269" tileid="270" tileid="271" tileid="272" tileid="295" tileid="296" tileid="297" tileid="298" tileid="299"/>
							<sdqnode id="444433" parentid="44443" recttop="250" rectleft="750" rectbottom="0" rectright="1000" bodyid="27" bodyid="31" bodyid="32" bodyid="33" bodyid="34" bodyid="35" tileid="295" tileid="296" tileid="297" tileid="298" tileid="299" tileid="322" tileid="323" tileid="324" tileid="325" tileid="326" tileid="357" tileid="358" tileid="359" tileid="360" tileid="361" tileid="394" tileid="395" tileid="396" tileid="397" tileid="422" tileid="423" tileid="424" tileid="425" tileid="426" tileid="452" tileid="453" tileid="488" tileid="489" tileid="490" tileid="491" tileid="492" tileid="493" tileid="494" tileid="495" tileid="496" tileid="570" tileid="571" tileid="572" tileid="573" tileid="574" tileid="575" tileid="576" tileid="577" tileid="578"/>
							<sdqnode id="444434" parentid="44443" recttop="250" rectleft="500" rectbottom="0" rectright="750" bodyid="26" bodyid="27" bodyid="28" bodyid="29" bodyid="30" tileid="294" tileid="321" tileid="356" tileid="392" tileid="393" tileid="419" tileid="420" tileid="421" tileid="448" tileid="449" tileid="450" tileid="451" tileid="480" tileid="481" tileid="482" tileid="483" tileid="484" tileid="485" tileid="486" tileid="487" tileid="488" tileid="562" tileid="563" tileid="564" tileid="565" tileid="566" tileid="567" tileid="568" tileid="569" tileid="570"/>
						</sdqnode>
						<sdqnode id="44444" parentid="4444" recttop="500" rectleft="0" rectbottom="0" rectright="500">
							<sdqnode id="444441" parentid="44444" recttop="500" rectleft="0" rectbottom="250" rectright="250" tileid="0" tileid="1" tileid="2" tileid="3" tileid="4" tileid="5" tileid="6" tileid="7" tileid="82" tileid="83" tileid="84" tileid="85" tileid="86" tileid="87" tileid="88" tileid="89" tileid="152" tileid="153" tileid="154" tileid="155" tileid="156" tileid="157" tileid="158" tileid="159" tileid="178" tileid="179" tileid="180" tileid="181" tileid="182" tileid="183" tileid="184" tileid="185" tileid="200" tileid="201" tileid="202" tileid="203" tileid="204" tileid="205" tileid="206" tileid="207" tileid="226" tileid="227" tileid="228" tileid="229" tileid="230" tileid="231" tileid="232" tileid="233" tileid="252" tileid="253" tileid="254" tileid="255" tileid="256" tileid="257" tileid="258" tileid="259" tileid="279" tileid="280" tileid="281" tileid="282" tileid="283" tileid="284" tileid="285" tileid="286"/>
							<sdqnode id="444442" parentid="44444" recttop="500" rectleft="250" rectbottom="250" rectright="500" bodyid="26" tileid="7" tileid="8" tileid="9" tileid="10" tileid="11" tileid="12" tileid="13" tileid="14" tileid="15" tileid="89" tileid="90" tileid="91" tileid="92" tileid="93" tileid="94" tileid="95" tileid="96" tileid="97" tileid="159" tileid="160" tileid="161" tileid="162" tileid="163" tileid="164" tileid="165" tileid="166" tileid="167" tileid="185" tileid="186" tileid="187" tileid="188" tileid="189" tileid="190" tileid="191" tileid="192" tileid="193" tileid="207" tileid="208" tileid="209" tileid="210" tileid="211" tileid="212" tileid="213" tileid="214" tileid="215" tileid="233" tileid="234" tileid="235" tileid="236" tileid="237" tileid="238" tileid="239" tileid="240" tileid="241" tileid="259" tileid="260" tileid="261" tileid="262" tileid="263" tileid="264" tileid="265" tileid="266" tileid="267" tileid="286" tileid="287" tileid="288" tileid="289" tileid="290" tileid="291" tileid="292" tileid="293" tileid="294"/>
							<sdqnode id="444443" parentid="44444" recttop="250" rectleft="250" rectbottom="0" rectright="500" bodyid="26" bodyid="27" tileid="286" tileid="287" tileid="288" tileid="289" tileid="290" tileid="291" tileid="292" tileid="293" tileid="294" tileid="313" tileid="314" tileid="315" tileid="316" tileid="317" tileid="318" tileid="319" tileid="320" tileid="321" tileid="348" tileid="349" tileid="350" tileid="351" tileid="352" tileid="353" tileid="354" tileid="355" tileid="356" tileid="384" tileid="385" tileid="386" tileid="387" tileid="388" tileid="389" tileid="390" tileid="391" tileid="392" tileid="411" tileid="412" tileid="413" tileid="414" tileid="415" tileid="416" tileid="417" tileid="418" tileid="419" tileid="440" tileid="441" tileid="442" tileid="443" tileid="444" tileid="445" tileid="446" tileid="447" tileid="448" tileid="472" tileid="473" tileid="474" tileid="475" tileid="476" tileid="477" tileid="478" tileid="479" tileid="480" tileid="554" tileid="555" tileid="556" tileid="557" tileid="558" tileid="559" tileid="560" tileid="561" tileid="562"/>
							<sdqnode id="444444" parentid="44444" recttop="250" rectleft="0" rectbottom="0" rectright="250" tileid="279" tileid="280" tileid="281" tileid="282" tileid="283" tileid="284" tileid="285" tileid="286" tileid="306" tileid="307" tileid="308" tileid="309" tileid="310" tileid="311" tileid="312" tileid="313" tileid="341" tileid="342" tileid="343" tileid="344" tileid="345" tileid="346" tileid="347" tileid="348" tileid="377" tileid="378" tileid="379" tileid="380" tileid="381" tileid="382" tileid="383" tileid="384" tileid="404" tileid="405" tileid="406" tileid="407" tileid="408" tileid="409" tileid="410" tileid="411" tileid="433" tileid="434" tileid="435" tileid="436" tileid="437" tileid="438" tileid="439" tileid="440" tileid="465" tileid="466" tileid="467" tileid="468" tileid="469" tileid="470" tileid="471" tileid="472" tileid="547" tileid="548" tileid="549" tileid="550" tileid="551" tileid="552" tileid="553" tileid="554"/>
						</sdqnode>
					</sdqnode>
				</sdqnode>
			</sdqnode>
		</sdqnode>
	</sdqnode>
</spacedivisionmap>

